{".class": "MypyFile", "_fullname": "sllurp.verb.inventory", "_name": null, "is_stub": false, "names": {".class": "SymbolTable", "LLRPClientFactory": {".class": "SymbolTableNode", "cross_ref": "sllurp.llrp.LLRPClientFactory", "kind": "Gdef"}, "Modulation_DefaultTari": {".class": "SymbolTableNode", "cross_ref": "sllurp.llrp_proto.Modulation_DefaultTari", "kind": "Gdef"}, "__doc__": {".class": "SymbolTableNode", "kind": "Gdef", "node": {".class": "Var", "flags": ["is_ready"], "fullname": "sllurp.verb.inventory.__doc__", "name": "__doc__", "type": "builtins.str"}}, "__file__": {".class": "SymbolTableNode", "kind": "Gdef", "node": {".class": "Var", "flags": ["is_ready"], "fullname": "sllurp.verb.inventory.__file__", "name": "__file__", "type": "builtins.str"}}, "__name__": {".class": "SymbolTableNode", "kind": "Gdef", "node": {".class": "Var", "flags": ["is_ready"], "fullname": "sllurp.verb.inventory.__name__", "name": "__name__", "type": "builtins.str"}}, "__package__": {".class": "SymbolTableNode", "kind": "Gdef", "node": {".class": "Var", "flags": ["is_ready"], "fullname": "sllurp.verb.inventory.__package__", "name": "__package__", "type": "builtins.str"}}, "defer": {".class": "SymbolTableNode", "kind": "Gdef", "node": {".class": "Var", "flags": ["is_ready", "is_suppressed_import"], "fullname": "sllurp.verb.inventory.defer", "name": "defer", "type": {".class": "AnyType"}}}, "division": {".class": "SymbolTableNode", "cross_ref": "__future__.division", "kind": "Gdef"}, "finish": {".class": "SymbolTableNode", "kind": "Gdef", "node": {".class": "FuncDef", "arg_kinds": [2], "arg_names": ["args"], "flags": [], "fullname": "sllurp.verb.inventory.finish", "name": "finish", "type": null}}, "logger": {".class": "SymbolTableNode", "kind": "Gdef", "node": {".class": "Var", "flags": [], "fullname": "sllurp.verb.inventory.logger", "name": "logger", "type": "logging.Logger"}}, "logging": {".class": "SymbolTableNode", "cross_ref": "logging", "kind": "ModuleRef"}, "logs": {".class": "SymbolTableNode", "kind": "Gdef", "node": {".class": "FuncDef", "arg_kinds": [2], "arg_names": ["args"], "flags": [], "fullname": "sllurp.verb.inventory.logs", "name": "logs", "type": null}}, "main": {".class": "SymbolTableNode", "kind": "Gdef", "node": {".class": "FuncDef", "arg_kinds": [0], "arg_names": ["args"], "flags": [], "fullname": "sllurp.verb.inventory.main", "name": "main", "type": null}}, "numtags": {".class": "SymbolTableNode", "kind": "Gdef", "node": {".class": "Var", "flags": ["is_ready"], "fullname": "sllurp.verb.inventory.numtags", "name": "numtags", "type": "builtins.int"}}, "pprint": {".class": "SymbolTableNode", "cross_ref": "pprint", "kind": "ModuleRef"}, "print_function": {".class": "SymbolTableNode", "cross_ref": "__future__.print_function", "kind": "Gdef"}, "reactor": {".class": "SymbolTableNode", "kind": "Gdef", "node": {".class": "Var", "flags": ["is_ready", "is_suppressed_import"], "fullname": "sllurp.verb.inventory.reactor", "name": "reactor", "type": {".class": "AnyType"}}}, "shutdown": {".class": "SymbolTableNode", "kind": "Gdef", "node": {".class": "FuncDef", "arg_kinds": [0], "arg_names": ["factory"], "flags": [], "fullname": "sllurp.verb.inventory.shutdown", "name": "shutdown", "type": null}}, "start_time": {".class": "SymbolTableNode", "kind": "Gdef", "node": {".class": "Var", "flags": [], "fullname": "sllurp.verb.inventory.start_time", "name": "start_time", "type": {".class": "AnyType"}}}, "tag_report_cb": {".class": "SymbolTableNode", "kind": "Gdef", "node": {".class": "FuncDef", "arg_kinds": [0], "arg_names": ["llrp_msg"], "flags": [], "fullname": "sllurp.verb.inventory.tag_report_cb", "name": "tag_report_cb", "type": null}}, "time": {".class": "SymbolTableNode", "cross_ref": "time", "kind": "ModuleRef"}}, "path": "/Users/colanconnan/tmp/rfid/sllurp/sllurp/verb/inventory.py"}
